rancho/__init__.py
rancho/__main__.py
rancho/misc/__init__.py
rancho/misc/icons.py
rancho/objects/choco.jpg
rancho/objects/jet copy.jpeg
rancho/objects/jet.jpeg
rancho/objects/music1.mp3
rancho/objects/music2.mp3
rancho/utils.py
rancho-1.0.2a0.dist-info/METADATA
rancho-1.0.2a0.dist-info/WHEEL
rancho-1.0.2a0.dist-info/RECORD
