Metadata-Version: 2.1
Name: rancho
Version: 1.0.2a0
Summary: Get the latest stoic quotes and a wish on the jet game
Author: Alagu Prakalya
Author-email: alagu.prakalya@gmail.com
Requires-Python: >=3.9
Classifier: Programming Language :: Python :: 3
Classifier: Programming Language :: Python :: 3.9
Classifier: Programming Language :: Python :: 3.10
Classifier: Programming Language :: Python :: 3.11
Classifier: Programming Language :: Python :: 3.12
Requires-Dist: pygame (>=2.5,<3.0)
